snag/__init__.py
snag/__main__.py
snag/config.py
snag/core.py
snag/fetch.py
snag/logger.py
snag-1.0.0.data/scripts/snag
snag-1.0.0.dist-info/LICENSE
snag-1.0.0.dist-info/METADATA
snag-1.0.0.dist-info/WHEEL
snag-1.0.0.dist-info/top_level.txt
snag-1.0.0.dist-info/RECORD
