Metadata-Version: 2.1
Name: snag
Version: 1.0.0
Summary: A tool to batch-download files from the internet
Home-page: https://github.com/willemhuntuvm/snag
Author: Willem Hunt
Author-email: whunt1@uvm.edu
License: MIT License
Platform: UNKNOWN
Classifier: Programming Language :: Python :: 3
Classifier: License :: OSI Approved :: MIT License
Classifier: Operating System :: OS Independent
Requires-Dist: beautifulsoup4
Requires-Dist: requests
